logic_plugin_manager/__init__.py
logic_plugin_manager/components/__init__.py
logic_plugin_manager/components/audiocomponent.py
logic_plugin_manager/components/component.py
logic_plugin_manager/defaults.py
logic_plugin_manager/exceptions.py
logic_plugin_manager/logic/__init__.py
logic_plugin_manager/logic/logic.py
logic_plugin_manager/logic/plugins.py
logic_plugin_manager/py.typed
logic_plugin_manager/tags/__init__.py
logic_plugin_manager/tags/category.py
logic_plugin_manager/tags/musicapps.py
logic_plugin_manager/tags/tagset.py
logic_plugin_manager-1.0.0.dist-info/WHEEL
logic_plugin_manager-1.0.0.dist-info/METADATA
logic_plugin_manager-1.0.0.dist-info/RECORD
