Metadata-Version: 2.3
Name: logic-plugin-manager
Version: 1.0.0
Summary: A utility for parsing and managing plugins in Logic Pro
Keywords: logic pro,audio plugins,au,plugin manager,music production
Author: h
Author-email: h <h@kotikot.com>
License: # License
Classifier: Intended Audience :: Developers
Classifier: Intended Audience :: End Users/Desktop
Classifier: Topic :: Multimedia :: Sound/Audio
Classifier: Topic :: Software Development :: Libraries :: Python Modules
Classifier: License :: OSI Approved :: GNU Affero General Public License v3 or later (AGPLv3+)
Classifier: License :: Other/Proprietary License
Classifier: Programming Language :: Python :: 3
Classifier: Programming Language :: Python :: 3.13
Classifier: Operating System :: MacOS
Classifier: Typing :: Typed
Requires-Dist: rapidfuzz>=3.14.3 ; extra == 'search'
Requires-Python: >=3.13
Project-URL: Commercial License, https://github.com/kotikotprojects/logic-plugin-manager/blob/main/LICENSE-COMMERCIAL.md
Project-URL: Homepage, https://git.kotikot.com/lib/logic-plugin-manager
Project-URL: Repository, https://github.com/kotikotprojects/logic-plugin-manager
Provides-Extra: search
